{
  "strategy": "fear_contrarian",
  "config": {
    "fng_entry_max": 20,
    "fng_exit_min": 50,
    "rsi_entry_max": 45,
    "rsi_exit_min": 65,
    "atr_trail": 3.0,
    "max_open": 3,
    "fee_rt": 0.004
  },
  "current_fng": 14,
  "results": {
    "2024": {
      "final_cap": 519.0317,
      "total_ret": 3.8063,
      "n_trades": 3,
      "trades_per_month": 0.3,
      "win_rate": 100.0,
      "profit_factor": 999.99,
      "max_dd": 2.242,
      "max_loss_streak": 0,
      "best_month": [
        "2024-08",
        19.03165608117252
      ],
      "worst_month": [
        "2024-08",
        19.03165608117252
      ],
      "avg_holding_hours": 144.0,
      "fng_below20_bars": 6,
      "fng_below20_days": 1.0,
      "exit_distribution": {
        "rsi_exit": 2,
        "trail_stop": 1
      },
      "fng_entry_dist": {
        "<10": 0,
        "10-15": 0,
        "15-20": 3
      },
      "monthly": {
        "2024-08": 19.0317
      },
      "trades": [
        {
          "ticker": "BTC-USD",
          "entry_ts": "2024-08-06 00:00:00",
          "exit_ts": "2024-08-08 20:00:00",
          "entry_px": 55693.6211,
          "exit_px": 61728.207,
          "pnl": 10.3924,
          "invest": 100.0,
          "win": true,
          "pnl_pct": 10.3924,
          "exit_reason": "rsi_exit:65",
          "entry_fng": 17,
          "exit_fng": 20,
          "bars_held": 18,
          "hours_held": 72
        },
        {
          "ticker": "DOGE-USD",
          "entry_ts": "2024-08-06 00:00:00",
          "exit_ts": "2024-08-11 00:00:00",
          "entry_px": 0.0986,
          "exit_px": 0.11,
          "pnl": 7.1052,
          "invest": 64.0,
          "win": true,
          "pnl_pct": 11.1019,
          "exit_reason": "rsi_exit:65",
          "entry_fng": 17,
          "exit_fng": 39,
          "bars_held": 31,
          "hours_held": 124
        },
        {
          "ticker": "ETH-USD",
          "entry_ts": "2024-08-06 00:00:00",
          "exit_ts": "2024-08-15 16:00:00",
          "entry_px": 2493.5596,
          "exit_px": 2551.5693,
          "pnl": 1.534,
          "invest": 80.0,
          "win": true,
          "pnl_pct": 1.9175,
          "exit_reason": "trail_stop",
          "entry_fng": 17,
          "exit_fng": 29,
          "bars_held": 59,
          "hours_held": 236
        }
      ]
    },
    "Val 2025": {
      "final_cap": 575.3977,
      "total_ret": 10.8598,
      "n_trades": 11,
      "trades_per_month": 1.2,
      "win_rate": 54.5455,
      "profit_factor": 3.0333,
      "max_dd": 6.1913,
      "max_loss_streak": 3,
      "best_month": [
        "2025-04",
        47.33353363414858
      ],
      "worst_month": [
        "2025-02",
        -20.639942665229842
      ],
      "avg_holding_hours": 124.4,
      "fng_below20_bars": 24,
      "fng_below20_days": 4.0,
      "exit_distribution": {
        "trail_stop": 5,
        "rsi_exit": 6
      },
      "fng_entry_dist": {
        "<10": 0,
        "10-15": 3,
        "15-20": 8
      },
      "monthly": {
        "2025-02": -20.6399,
        "2025-03": 29.6724,
        "2025-04": 47.3335
      },
      "trades": [
        {
          "ticker": "BTC-USD",
          "entry_ts": "2025-02-27 00:00:00",
          "exit_ts": "2025-02-28 00:00:00",
          "entry_px": 85164.9922,
          "exit_px": 80283.3203,
          "pnl": -9.5118,
          "invest": 155.7095,
          "win": false,
          "pnl_pct": -6.1087,
          "exit_reason": "trail_stop",
          "entry_fng": 10,
          "exit_fng": 16,
          "bars_held": 7,
          "hours_held": 28
        },
        {
          "ticker": "ETH-USD",
          "entry_ts": "2025-02-27 00:00:00",
          "exit_ts": "2025-02-28 04:00:00",
          "entry_px": 2332.29,
          "exit_px": 2102.575,
          "pnl": -11.1281,
          "invest": 108.9966,
          "win": false,
          "pnl_pct": -10.2096,
          "exit_reason": "trail_stop",
          "entry_fng": 10,
          "exit_fng": 16,
          "bars_held": 8,
          "hours_held": 32
        },
        {
          "ticker": "SOL-USD",
          "entry_ts": "2025-02-27 00:00:00",
          "exit_ts": "2025-03-02 12:00:00",
          "entry_px": 138.6938,
          "exit_px": 157.3261,
          "pnl": 9.9041,
          "invest": 76.2977,
          "win": true,
          "pnl_pct": 12.9809,
          "exit_reason": "rsi_exit:66",
          "entry_fng": 10,
          "exit_fng": 26,
          "bars_held": 22,
          "hours_held": 88
        },
        {
          "ticker": "DOGE-USD",
          "entry_ts": "2025-02-28 00:00:00",
          "exit_ts": "2025-03-02 16:00:00",
          "entry_px": 0.1898,
          "exit_px": 0.2321,
          "pnl": 14.1028,
          "invest": 64.8451,
          "win": true,
          "pnl_pct": 21.7484,
          "exit_reason": "rsi_exit:72",
          "entry_fng": 16,
          "exit_fng": 26,
          "bars_held": 17,
          "hours_held": 68
        },
        {
          "ticker": "BTC-USD",
          "entry_ts": "2025-02-28 04:00:00",
          "exit_ts": "2025-03-02 16:00:00",
          "entry_px": 79049.0703,
          "exit_px": 93525.1016,
          "pnl": 12.7466,
          "invest": 71.4498,
          "win": true,
          "pnl_pct": 17.8399,
          "exit_reason": "rsi_exit:72",
          "entry_fng": 16,
          "exit_fng": 26,
          "bars_held": 16,
          "hours_held": 64
        },
        {
          "ticker": "BTC-USD",
          "entry_ts": "2025-03-04 00:00:00",
          "exit_ts": "2025-03-09 12:00:00",
          "entry_px": 84031.1875,
          "exit_px": 83052.2109,
          "pnl": -1.6696,
          "invest": 107.029,
          "win": false,
          "pnl_pct": -1.56,
          "exit_reason": "trail_stop",
          "entry_fng": 15,
          "exit_fng": 27,
          "bars_held": 34,
          "hours_held": 136
        },
        {
          "ticker": "SOL-USD",
          "entry_ts": "2025-03-04 00:00:00",
          "exit_ts": "2025-03-09 12:00:00",
          "entry_px": 136.9335,
          "exit_px": 130.1134,
          "pnl": -3.6717,
          "invest": 68.4986,
          "win": false,
          "pnl_pct": -5.3603,
          "exit_reason": "trail_stop",
          "entry_fng": 15,
          "exit_fng": 27,
          "bars_held": 34,
          "hours_held": 136
        },
        {
          "ticker": "ETH-USD",
          "entry_ts": "2025-03-04 00:00:00",
          "exit_ts": "2025-03-09 16:00:00",
          "entry_px": 2076.0122,
          "exit_px": 2041.9915,
          "pnl": -1.7397,
          "invest": 85.6232,
          "win": false,
          "pnl_pct": -2.0318,
          "exit_reason": "trail_stop",
          "entry_fng": 15,
          "exit_fng": 27,
          "bars_held": 35,
          "hours_held": 140
        },
        {
          "ticker": "SOL-USD",
          "entry_ts": "2025-04-09 00:00:00",
          "exit_ts": "2025-04-12 12:00:00",
          "entry_px": 103.2965,
          "exit_px": 130.4696,
          "pnl": 17.4396,
          "invest": 67.5922,
          "win": true,
          "pnl_pct": 25.8011,
          "exit_reason": "rsi_exit:71",
          "entry_fng": 18,
          "exit_fng": 43,
          "bars_held": 22,
          "hours_held": 88
        },
        {
          "ticker": "BTC-USD",
          "entry_ts": "2025-04-09 00:00:00",
          "exit_ts": "2025-04-21 00:00:00",
          "entry_px": 75003.0312,
          "exit_px": 87203.0547,
          "pnl": 16.6883,
          "invest": 105.6128,
          "win": true,
          "pnl_pct": 15.8014,
          "exit_reason": "rsi_exit:72",
          "entry_fng": 18,
          "exit_fng": 39,
          "bars_held": 73,
          "hours_held": 292
        },
        {
          "ticker": "ETH-USD",
          "entry_ts": "2025-04-09 00:00:00",
          "exit_ts": "2025-04-21 04:00:00",
          "entry_px": 1417.3787,
          "exit_px": 1645.4868,
          "pnl": 13.2056,
          "invest": 84.4903,
          "win": true,
          "pnl_pct": 15.6298,
          "exit_reason": "rsi_exit:65",
          "entry_fng": 18,
          "exit_fng": 39,
          "bars_held": 74,
          "hours_held": 296
        }
      ]
    },
    "Finale": {
      "final_cap": 500.7261,
      "total_ret": -12.9774,
      "n_trades": 70,
      "trades_per_month": 8.2,
      "win_rate": 40.0,
      "profit_factor": 0.7055,
      "max_dd": 24.0722,
      "max_loss_streak": 11,
      "best_month": [
        "2026-03",
        17.124693025117175
      ],
      "worst_month": [
        "2025-11",
        -40.38472026526599
      ],
      "avg_holding_hours": 92.7,
      "fng_below20_bars": 564,
      "fng_below20_days": 94.0,
      "exit_distribution": {
        "trail_stop": 48,
        "rsi_exit": 22
      },
      "fng_entry_dist": {
        "<10": 9,
        "10-15": 34,
        "15-20": 27
      },
      "monthly": {
        "2025-11": -40.3847,
        "2025-12": -7.7367,
        "2026-01": -16.9623,
        "2026-02": -33.8188,
        "2026-03": 17.1247,
        "2026-04": 16.2238,
        "2026-06": -9.1175
      },
      "trades": [
        {
          "ticker": "BTC-USD",
          "entry_ts": "2025-11-13 00:00:00",
          "exit_ts": "2025-11-13 16:00:00",
          "entry_px": 102291.6562,
          "exit_px": 98650.9922,
          "pnl": -4.5393,
          "invest": 115.0795,
          "win": false,
          "pnl_pct": -3.9445,
          "exit_reason": "trail_stop",
          "entry_fng": 15,
          "exit_fng": 15,
          "bars_held": 5,
          "hours_held": 20
        },
        {
          "ticker": "SOL-USD",
          "entry_ts": "2025-11-13 00:00:00",
          "exit_ts": "2025-11-13 16:00:00",
          "entry_px": 154.9481,
          "exit_px": 142.8019,
          "pnl": -7.5558,
          "invest": 92.0636,
          "win": false,
          "pnl_pct": -8.2071,
          "exit_reason": "trail_stop",
          "entry_fng": 15,
          "exit_fng": 15,
          "bars_held": 5,
          "hours_held": 20
        },
        {
          "ticker": "ETH-USD",
          "entry_ts": "2025-11-13 12:00:00",
          "exit_ts": "2025-11-14 08:00:00",
          "entry_px": 3378.1301,
          "exit_px": 3135.8357,
          "pnl": -5.5558,
          "invest": 73.6509,
          "win": false,
          "pnl_pct": -7.5434,
          "exit_reason": "trail_stop",
          "entry_fng": 15,
          "exit_fng": 16,
          "bars_held": 6,
          "hours_held": 24
        },
        {
          "ticker": "BTC-USD",
          "entry_ts": "2025-11-13 20:00:00",
          "exit_ts": "2025-11-14 20:00:00",
          "entry_px": 99694.7031,
          "exit_px": 94420.4688,
          "pnl": -4.4412,
          "invest": 78.3443,
          "win": false,
          "pnl_pct": -5.6688,
          "exit_reason": "trail_stop",
          "entry_fng": 15,
          "exit_fng": 16,
          "bars_held": 7,
          "hours_held": 28
        },
        {
          "ticker": "DOGE-USD",
          "entry_ts": "2025-11-13 16:00:00",
          "exit_ts": "2025-11-21 08:00:00",
          "entry_px": 0.161,
          "exit_px": 0.1365,
          "pnl": -15.2109,
          "invest": 97.9303,
          "win": false,
          "pnl_pct": -15.5323,
          "exit_reason": "trail_stop",
          "entry_fng": 15,
          "exit_fng": 14,
          "bars_held": 23,
          "hours_held": 92
        },
        {
          "ticker": "SOL-USD",
          "entry_ts": "2025-11-14 08:00:00",
          "exit_ts": "2025-11-21 08:00:00",
          "entry_px": 140.4198,
          "exit_px": 123.9733,
          "pnl": -9.2051,
          "invest": 76.2944,
          "win": false,
          "pnl_pct": -12.0652,
          "exit_reason": "trail_stop",
          "entry_fng": 16,
          "exit_fng": 14,
          "bars_held": 19,
          "hours_held": 76
        },
        {
          "ticker": "ETH-USD",
          "entry_ts": "2025-11-14 20:00:00",
          "exit_ts": "2025-11-21 08:00:00",
          "entry_px": 3104.2302,
          "exit_px": 2684.1687,
          "pnl": -10.5213,
          "invest": 75.8162,
          "win": false,
          "pnl_pct": -13.8774,
          "exit_reason": "trail_stop",
          "entry_fng": 16,
          "exit_fng": 14,
          "bars_held": 16,
          "hours_held": 64
        },
        {
          "ticker": "BTC-USD",
          "entry_ts": "2025-11-21 08:00:00",
          "exit_ts": "2025-11-27 04:00:00",
          "entry_px": 82228.7734,
          "exit_px": 91395.1016,
          "pnl": 16.6446,
          "invest": 155.5105,
          "win": true,
          "pnl_pct": 10.7032,
          "exit_reason": "rsi_exit:65",
          "entry_fng": 14,
          "exit_fng": 22,
          "bars_held": 36,
          "hours_held": 144
        },
        {
          "ticker": "ETH-USD",
          "entry_ts": "2025-11-21 12:00:00",
          "exit_ts": "2025-12-01 04:00:00",
          "entry_px": 2698.9119,
          "exit_px": 2840.8213,
          "pnl": 5.2659,
          "invest": 108.8573,
          "win": true,
          "pnl_pct": 4.8374,
          "exit_reason": "trail_stop",
          "entry_fng": 14,
          "exit_fng": 24,
          "bars_held": 47,
          "hours_held": 188
        },
        {
          "ticker": "SOL-USD",
          "entry_ts": "2025-11-21 12:00:00",
          "exit_ts": "2025-12-01 04:00:00",
          "entry_px": 125.1989,
          "exit_px": 127.3573,
          "pnl": 1.0039,
          "invest": 76.2001,
          "win": true,
          "pnl_pct": 1.3175,
          "exit_reason": "trail_stop",
          "entry_fng": 14,
          "exit_fng": 24,
          "bars_held": 47,
          "hours_held": 188
        },
        {
          "ticker": "DOGE-USD",
          "entry_ts": "2025-12-15 00:00:00",
          "exit_ts": "2025-12-15 12:00:00",
          "entry_px": 0.1364,
          "exit_px": 0.1306,
          "pnl": -3.1787,
          "invest": 69.2842,
          "win": false,
          "pnl_pct": -4.5879,
          "exit_reason": "trail_stop",
          "entry_fng": 16,
          "exit_fng": 16,
          "bars_held": 4,
          "hours_held": 16
        },
        {
          "ticker": "BTC-USD",
          "entry_ts": "2025-12-15 00:00:00",
          "exit_ts": "2025-12-15 16:00:00",
          "entry_px": 89300.5547,
          "exit_px": 86203.125,
          "pnl": -4.1725,
          "invest": 108.2566,
          "win": false,
          "pnl_pct": -3.8543,
          "exit_reason": "trail_stop",
          "entry_fng": 16,
          "exit_fng": 16,
          "bars_held": 5,
          "hours_held": 20
        },
        {
          "ticker": "SOL-USD",
          "entry_ts": "2025-12-15 00:00:00",
          "exit_ts": "2025-12-15 16:00:00",
          "entry_px": 131.2337,
          "exit_px": 125.1298,
          "pnl": -4.3582,
          "invest": 86.6052,
          "win": false,
          "pnl_pct": -5.0322,
          "exit_reason": "trail_stop",
          "entry_fng": 16,
          "exit_fng": 16,
          "bars_held": 5,
          "hours_held": 20
        },
        {
          "ticker": "ETH-USD",
          "entry_ts": "2025-12-15 12:00:00",
          "exit_ts": "2025-12-17 16:00:00",
          "entry_px": 3005.4951,
          "exit_px": 2817.4885,
          "pnl": -4.5514,
          "invest": 68.6485,
          "win": false,
          "pnl_pct": -6.63,
          "exit_reason": "trail_stop",
          "entry_fng": 16,
          "exit_fng": 16,
          "bars_held": 14,
          "hours_held": 56
        },
        {
          "ticker": "DOGE-USD",
          "entry_ts": "2025-12-15 16:00:00",
          "exit_ts": "2025-12-18 00:00:00",
          "entry_px": 0.1289,
          "exit_px": 0.1254,
          "pnl": -2.896,
          "invest": 92.185,
          "win": false,
          "pnl_pct": -3.1415,
          "exit_reason": "trail_stop",
          "entry_fng": 16,
          "exit_fng": 17,
          "bars_held": 15,
          "hours_held": 60
        },
        {
          "ticker": "BTC-USD",
          "entry_ts": "2025-12-15 20:00:00",
          "exit_ts": "2025-12-18 16:00:00",
          "entry_px": 86422.1875,
          "exit_px": 84542.4453,
          "pnl": -1.8924,
          "invest": 73.748,
          "win": false,
          "pnl_pct": -2.566,
          "exit_reason": "trail_stop",
          "entry_fng": 16,
          "exit_fng": 17,
          "bars_held": 18,
          "hours_held": 72
        },
        {
          "ticker": "SOL-USD",
          "entry_ts": "2025-12-17 16:00:00",
          "exit_ts": "2025-12-18 16:00:00",
          "entry_px": 122.316,
          "exit_px": 117.7573,
          "pnl": -2.9529,
          "invest": 71.8178,
          "win": false,
          "pnl_pct": -4.1117,
          "exit_reason": "trail_stop",
          "entry_fng": 16,
          "exit_fng": 17,
          "bars_held": 7,
          "hours_held": 28
        },
        {
          "ticker": "ETH-USD",
          "entry_ts": "2025-12-18 00:00:00",
          "exit_ts": "2025-12-18 16:00:00",
          "entry_px": 2830.1121,
          "exit_px": 2783.9741,
          "pnl": -1.5238,
          "invest": 75.312,
          "win": false,
          "pnl_pct": -2.0233,
          "exit_reason": "trail_stop",
          "entry_fng": 17,
          "exit_fng": 17,
          "bars_held": 5,
          "hours_held": 20
        },
        {
          "ticker": "BTC-USD",
          "entry_ts": "2025-12-18 20:00:00",
          "exit_ts": "2025-12-22 08:00:00",
          "entry_px": 85476.1328,
          "exit_px": 89919.9062,
          "pnl": 3.9432,
          "invest": 82.5211,
          "win": true,
          "pnl_pct": 4.7785,
          "exit_reason": "rsi_exit:65",
          "entry_fng": 17,
          "exit_fng": 25,
          "bars_held": 22,
          "hours_held": 88
        },
        {
          "ticker": "ETH-USD",
          "entry_ts": "2025-12-18 20:00:00",
          "exit_ts": "2025-12-23 12:00:00",
          "entry_px": 2827.4104,
          "exit_px": 2926.4688,
          "pnl": 2.0399,
          "invest": 66.0169,
          "win": true,
          "pnl_pct": 3.0899,
          "exit_reason": "trail_stop",
          "entry_fng": 17,
          "exit_fng": 24,
          "bars_held": 29,
          "hours_held": 116
        },
        {
          "ticker": "DOGE-USD",
          "entry_ts": "2025-12-18 16:00:00",
          "exit_ts": "2025-12-24 04:00:00",
          "entry_px": 0.1202,
          "exit_px": 0.1272,
          "pnl": 5.5362,
          "invest": 103.1514,
          "win": true,
          "pnl_pct": 5.3671,
          "exit_reason": "trail_stop",
          "entry_fng": 17,
          "exit_fng": 24,
          "bars_held": 34,
          "hours_held": 136
        },
        {
          "ticker": "ETH-USD",
          "entry_ts": "2026-01-30 00:00:00",
          "exit_ts": "2026-01-31 12:00:00",
          "entry_px": 2737.6411,
          "exit_px": 2525.4329,
          "pnl": -6.8505,
          "invest": 84.3642,
          "win": false,
          "pnl_pct": -8.1201,
          "exit_reason": "trail_stop",
          "entry_fng": 16,
          "exit_fng": 20,
          "bars_held": 10,
          "hours_held": 40
        },
        {
          "ticker": "SOL-USD",
          "entry_ts": "2026-01-30 00:00:00",
          "exit_ts": "2026-01-31 12:00:00",
          "entry_px": 114.4199,
          "exit_px": 108.6914,
          "pnl": -3.6352,
          "invest": 67.4914,
          "win": false,
          "pnl_pct": -5.3861,
          "exit_reason": "trail_stop",
          "entry_fng": 16,
          "exit_fng": 20,
          "bars_held": 10,
          "hours_held": 40
        },
        {
          "ticker": "BTC-USD",
          "entry_ts": "2026-01-30 00:00:00",
          "exit_ts": "2026-01-31 16:00:00",
          "entry_px": 82581.6641,
          "exit_px": 77820.7422,
          "pnl": -6.4767,
          "invest": 105.4552,
          "win": false,
          "pnl_pct": -6.1417,
          "exit_reason": "trail_stop",
          "entry_fng": 16,
          "exit_fng": 20,
          "bars_held": 11,
          "hours_held": 44
        },
        {
          "ticker": "SOL-USD",
          "entry_ts": "2026-02-01 00:00:00",
          "exit_ts": "2026-02-04 08:00:00",
          "entry_px": 104.7937,
          "exit_px": 96.0808,
          "pnl": -6.5119,
          "invest": 75.0161,
          "win": false,
          "pnl_pct": -8.6807,
          "exit_reason": "trail_stop",
          "entry_fng": 14,
          "exit_fng": 14,
          "bars_held": 21,
          "hours_held": 84
        },
        {
          "ticker": "ETH-USD",
          "entry_ts": "2026-02-01 00:00:00",
          "exit_ts": "2026-02-04 12:00:00",
          "entry_px": 2442.4265,
          "exit_px": 2151.6814,
          "pnl": -13.1342,
          "invest": 107.1659,
          "win": false,
          "pnl_pct": -12.256,
          "exit_reason": "trail_stop",
          "entry_fng": 14,
          "exit_fng": 14,
          "bars_held": 22,
          "hours_held": 88
        },
        {
          "ticker": "BTC-USD",
          "entry_ts": "2026-02-01 00:00:00",
          "exit_ts": "2026-02-04 16:00:00",
          "entry_px": 78803.3438,
          "exit_px": 73782.9141,
          "pnl": -10.3262,
          "invest": 153.0942,
          "win": false,
          "pnl_pct": -6.745,
          "exit_reason": "trail_stop",
          "entry_fng": 14,
          "exit_fng": 14,
          "bars_held": 23,
          "hours_held": 92
        },
        {
          "ticker": "SOL-USD",
          "entry_ts": "2026-02-04 12:00:00",
          "exit_ts": "2026-02-05 12:00:00",
          "entry_px": 92.5916,
          "exit_px": 84.4616,
          "pnl": -9.2613,
          "invest": 101.2721,
          "win": false,
          "pnl_pct": -9.1449,
          "exit_reason": "trail_stop",
          "entry_fng": 14,
          "exit_fng": 12,
          "bars_held": 7,
          "hours_held": 28
        },
        {
          "ticker": "DOGE-USD",
          "entry_ts": "2026-02-04 12:00:00",
          "exit_ts": "2026-02-05 12:00:00",
          "entry_px": 0.1032,
          "exit_px": 0.0943,
          "pnl": -6.3727,
          "invest": 70.8904,
          "win": false,
          "pnl_pct": -8.9895,
          "exit_reason": "trail_stop",
          "entry_fng": 14,
          "exit_fng": 12,
          "bars_held": 7,
          "hours_held": 28
        },
        {
          "ticker": "ETH-USD",
          "entry_ts": "2026-02-04 16:00:00",
          "exit_ts": "2026-02-05 20:00:00",
          "entry_px": 2183.3596,
          "exit_px": 1821.1294,
          "pnl": -15.6467,
          "invest": 92.4537,
          "win": false,
          "pnl_pct": -16.9238,
          "exit_reason": "trail_stop",
          "entry_fng": 14,
          "exit_fng": 12,
          "bars_held": 8,
          "hours_held": 32
        },
        {
          "ticker": "SOL-USD",
          "entry_ts": "2026-02-05 16:00:00",
          "exit_ts": "2026-02-11 12:00:00",
          "entry_px": 81.5138,
          "exit_px": 79.8876,
          "pnl": -1.8657,
          "invest": 78.1733,
          "win": false,
          "pnl_pct": -2.3866,
          "exit_reason": "trail_stop",
          "entry_fng": 12,
          "exit_fng": 11,
          "bars_held": 36,
          "hours_held": 144
        },
        {
          "ticker": "BTC-USD",
          "entry_ts": "2026-02-05 12:00:00",
          "exit_ts": "2026-02-12 16:00:00",
          "entry_px": 67298.3125,
          "exit_px": 65781.4141,
          "pnl": -2.9534,
          "invest": 111.6762,
          "win": false,
          "pnl_pct": -2.6446,
          "exit_reason": "trail_stop",
          "entry_fng": 12,
          "exit_fng": 5,
          "bars_held": 44,
          "hours_held": 176
        },
        {
          "ticker": "DOGE-USD",
          "entry_ts": "2026-02-05 20:00:00",
          "exit_ts": "2026-02-14 08:00:00",
          "entry_px": 0.0883,
          "exit_px": 0.1007,
          "pnl": 10.5834,
          "invest": 77.7634,
          "win": true,
          "pnl_pct": 13.6097,
          "exit_reason": "rsi_exit:71",
          "entry_fng": 12,
          "exit_fng": 9,
          "bars_held": 52,
          "hours_held": 208
        },
        {
          "ticker": "SOL-USD",
          "entry_ts": "2026-02-12 16:00:00",
          "exit_ts": "2026-02-14 16:00:00",
          "entry_px": 77.581,
          "exit_px": 88.1508,
          "pnl": 15.2328,
          "invest": 115.6607,
          "win": true,
          "pnl_pct": 13.1703,
          "exit_reason": "rsi_exit:66",
          "entry_fng": 5,
          "exit_fng": 9,
          "bars_held": 13,
          "hours_held": 52
        },
        {
          "ticker": "ETH-USD",
          "entry_ts": "2026-02-11 12:00:00",
          "exit_ts": "2026-02-15 16:00:00",
          "entry_px": 1930.6952,
          "exit_px": 1943.3979,
          "pnl": 0.1977,
          "invest": 77.3267,
          "win": true,
          "pnl_pct": 0.2557,
          "exit_reason": "trail_stop",
          "entry_fng": 11,
          "exit_fng": 8,
          "bars_held": 26,
          "hours_held": 104
        },
        {
          "ticker": "SOL-USD",
          "entry_ts": "2026-02-16 12:00:00",
          "exit_ts": "2026-02-19 12:00:00",
          "entry_px": 83.1658,
          "exit_px": 80.52,
          "pnl": -2.1142,
          "invest": 59.2522,
          "win": false,
          "pnl_pct": -3.5682,
          "exit_reason": "trail_stop",
          "entry_fng": 12,
          "exit_fng": 9,
          "bars_held": 19,
          "hours_held": 76
        },
        {
          "ticker": "ETH-USD",
          "entry_ts": "2026-02-15 20:00:00",
          "exit_ts": "2026-02-23 00:00:00",
          "entry_px": 1965.9232,
          "exit_px": 1863.0763,
          "pnl": -10.5529,
          "invest": 188.1023,
          "win": false,
          "pnl_pct": -5.6102,
          "exit_reason": "trail_stop",
          "entry_fng": 8,
          "exit_fng": 5,
          "bars_held": 44,
          "hours_held": 176
        },
        {
          "ticker": "BTC-USD",
          "entry_ts": "2026-02-16 12:00:00",
          "exit_ts": "2026-02-23 00:00:00",
          "entry_px": 67508.2969,
          "exit_px": 64946.3633,
          "pnl": -3.5377,
          "invest": 84.646,
          "win": false,
          "pnl_pct": -4.1794,
          "exit_reason": "trail_stop",
          "entry_fng": 12,
          "exit_fng": 5,
          "bars_held": 40,
          "hours_held": 160
        },
        {
          "ticker": "DOGE-USD",
          "entry_ts": "2026-02-19 12:00:00",
          "exit_ts": "2026-02-23 00:00:00",
          "entry_px": 0.0968,
          "exit_px": 0.093,
          "pnl": -3.4127,
          "invest": 78.1573,
          "win": false,
          "pnl_pct": -4.3665,
          "exit_reason": "trail_stop",
          "entry_fng": 9,
          "exit_fng": 5,
          "bars_held": 22,
          "hours_held": 88
        },
        {
          "ticker": "BTC-USD",
          "entry_ts": "2026-02-23 04:00:00",
          "exit_ts": "2026-02-24 04:00:00",
          "entry_px": 65941.9375,
          "exit_px": 63134.9609,
          "pnl": -5.0176,
          "invest": 108.1532,
          "win": false,
          "pnl_pct": -4.6393,
          "exit_reason": "trail_stop",
          "entry_fng": 5,
          "exit_fng": 8,
          "bars_held": 7,
          "hours_held": 28
        },
        {
          "ticker": "SOL-USD",
          "entry_ts": "2026-02-23 00:00:00",
          "exit_ts": "2026-02-25 12:00:00",
          "entry_px": 77.8746,
          "exit_px": 85.9836,
          "pnl": 17.9746,
          "invest": 180.2553,
          "win": true,
          "pnl_pct": 9.9718,
          "exit_reason": "rsi_exit:67",
          "entry_fng": 5,
          "exit_fng": 11,
          "bars_held": 16,
          "hours_held": 64
        },
        {
          "ticker": "ETH-USD",
          "entry_ts": "2026-02-23 04:00:00",
          "exit_ts": "2026-02-25 12:00:00",
          "entry_px": 1884.7643,
          "exit_px": 2010.161,
          "pnl": 4.0408,
          "invest": 64.8919,
          "win": true,
          "pnl_pct": 6.227,
          "exit_reason": "rsi_exit:66",
          "entry_fng": 5,
          "exit_fng": 11,
          "bars_held": 15,
          "hours_held": 60
        },
        {
          "ticker": "DOGE-USD",
          "entry_ts": "2026-02-24 04:00:00",
          "exit_ts": "2026-02-25 12:00:00",
          "entry_px": 0.0912,
          "exit_px": 0.1017,
          "pnl": 8.859,
          "invest": 80.1894,
          "win": true,
          "pnl_pct": 11.0476,
          "exit_reason": "rsi_exit:69",
          "entry_fng": 8,
          "exit_fng": 11,
          "bars_held": 9,
          "hours_held": 36
        },
        {
          "ticker": "DOGE-USD",
          "entry_ts": "2026-02-27 08:00:00",
          "exit_ts": "2026-03-04 00:00:00",
          "entry_px": 0.095,
          "exit_px": 0.0891,
          "pnl": -9.4397,
          "invest": 142.9485,
          "win": false,
          "pnl_pct": -6.6036,
          "exit_reason": "trail_stop",
          "entry_fng": 13,
          "exit_fng": 10,
          "bars_held": 29,
          "hours_held": 116
        },
        {
          "ticker": "ETH-USD",
          "entry_ts": "2026-02-27 12:00:00",
          "exit_ts": "2026-03-04 12:00:00",
          "entry_px": 1948.6323,
          "exit_px": 2155.6658,
          "pnl": 10.189,
          "invest": 100.064,
          "win": true,
          "pnl_pct": 10.1825,
          "exit_reason": "rsi_exit:69",
          "entry_fng": 13,
          "exit_fng": 10,
          "bars_held": 31,
          "hours_held": 124
        },
        {
          "ticker": "SOL-USD",
          "entry_ts": "2026-02-27 12:00:00",
          "exit_ts": "2026-03-04 12:00:00",
          "entry_px": 82.7695,
          "exit_px": 92.562,
          "pnl": 7.974,
          "invest": 70.0448,
          "win": true,
          "pnl_pct": 11.3842,
          "exit_reason": "rsi_exit:67",
          "entry_fng": 13,
          "exit_fng": 10,
          "bars_held": 31,
          "hours_held": 124
        },
        {
          "ticker": "DOGE-USD",
          "entry_ts": "2026-03-04 04:00:00",
          "exit_ts": "2026-03-04 16:00:00",
          "entry_px": 0.09,
          "exit_px": 0.1031,
          "pnl": 12.525,
          "invest": 89.084,
          "win": true,
          "pnl_pct": 14.0597,
          "exit_reason": "rsi_exit:71",
          "entry_fng": 10,
          "exit_fng": 10,
          "bars_held": 4,
          "hours_held": 16
        },
        {
          "ticker": "BTC-USD",
          "entry_ts": "2026-03-06 12:00:00",
          "exit_ts": "2026-03-10 12:00:00",
          "entry_px": 68543.0312,
          "exit_px": 71360.6641,
          "pnl": 3.678,
          "invest": 99.5487,
          "win": true,
          "pnl_pct": 3.6947,
          "exit_reason": "rsi_exit:67",
          "entry_fng": 18,
          "exit_fng": 13,
          "bars_held": 25,
          "hours_held": 100
        },
        {
          "ticker": "ETH-USD",
          "entry_ts": "2026-03-06 12:00:00",
          "exit_ts": "2026-03-13 00:00:00",
          "entry_px": 1977.0292,
          "exit_px": 2118.7517,
          "pnl": 5.3678,
          "invest": 79.639,
          "win": true,
          "pnl_pct": 6.7402,
          "exit_reason": "rsi_exit:65",
          "entry_fng": 18,
          "exit_fng": 15,
          "bars_held": 40,
          "hours_held": 160
        },
        {
          "ticker": "SOL-USD",
          "entry_ts": "2026-03-06 12:00:00",
          "exit_ts": "2026-03-13 00:00:00",
          "entry_px": 84.6384,
          "exit_px": 89.7339,
          "pnl": 3.5657,
          "invest": 63.7112,
          "win": true,
          "pnl_pct": 5.5966,
          "exit_reason": "rsi_exit:65",
          "entry_fng": 18,
          "exit_fng": 15,
          "bars_held": 40,
          "hours_held": 160
        },
        {
          "ticker": "ETH-USD",
          "entry_ts": "2026-03-20 00:00:00",
          "exit_ts": "2026-03-23 04:00:00",
          "entry_px": 2152.6963,
          "exit_px": 2044.3658,
          "pnl": -5.8001,
          "invest": 107.1746,
          "win": false,
          "pnl_pct": -5.4118,
          "exit_reason": "trail_stop",
          "entry_fng": 11,
          "exit_fng": 8,
          "bars_held": 20,
          "hours_held": 80
        },
        {
          "ticker": "DOGE-USD",
          "entry_ts": "2026-03-20 00:00:00",
          "exit_ts": "2026-03-26 08:00:00",
          "entry_px": 0.0942,
          "exit_px": 0.0913,
          "pnl": -2.5403,
          "invest": 75.0222,
          "win": false,
          "pnl_pct": -3.3861,
          "exit_reason": "trail_stop",
          "entry_fng": 11,
          "exit_fng": 10,
          "bars_held": 39,
          "hours_held": 156
        },
        {
          "ticker": "SOL-USD",
          "entry_ts": "2026-03-23 04:00:00",
          "exit_ts": "2026-03-26 08:00:00",
          "entry_px": 86.0534,
          "exit_px": 87.6208,
          "pnl": 1.564,
          "invest": 110.5705,
          "win": true,
          "pnl_pct": 1.4145,
          "exit_reason": "trail_stop",
          "entry_fng": 8,
          "exit_fng": 10,
          "bars_held": 20,
          "hours_held": 80
        },
        {
          "ticker": "BTC-USD",
          "entry_ts": "2026-03-20 00:00:00",
          "exit_ts": "2026-03-27 04:00:00",
          "entry_px": 70747.9531,
          "exit_px": 68418.7266,
          "pnl": -5.6324,
          "invest": 153.1065,
          "win": false,
          "pnl_pct": -3.6787,
          "exit_reason": "trail_stop",
          "entry_fng": 11,
          "exit_fng": 13,
          "bars_held": 44,
          "hours_held": 176
        },
        {
          "ticker": "SOL-USD",
          "entry_ts": "2026-03-26 12:00:00",
          "exit_ts": "2026-03-27 16:00:00",
          "entry_px": 87.5657,
          "exit_px": 82.7488,
          "pnl": -4.3265,
          "invest": 73.5992,
          "win": false,
          "pnl_pct": -5.8785,
          "exit_reason": "trail_stop",
          "entry_fng": 10,
          "exit_fng": 13,
          "bars_held": 8,
          "hours_held": 32
        },
        {
          "ticker": "ETH-USD",
          "entry_ts": "2026-03-26 08:00:00",
          "exit_ts": "2026-04-01 08:00:00",
          "entry_px": 2067.5249,
          "exit_px": 2134.9307,
          "pnl": 2.994,
          "invest": 105.1417,
          "win": true,
          "pnl_pct": 2.8476,
          "exit_reason": "rsi_exit:65",
          "entry_fng": 10,
          "exit_fng": 8,
          "bars_held": 37,
          "hours_held": 148
        },
        {
          "ticker": "BTC-USD",
          "entry_ts": "2026-03-27 16:00:00",
          "exit_ts": "2026-04-05 20:00:00",
          "entry_px": 66041.4531,
          "exit_px": 68982.9141,
          "pnl": 3.5447,
          "invest": 87.815,
          "win": true,
          "pnl_pct": 4.0366,
          "exit_reason": "rsi_exit:69",
          "entry_fng": 13,
          "exit_fng": 12,
          "bars_held": 56,
          "hours_held": 224
        },
        {
          "ticker": "SOL-USD",
          "entry_ts": "2026-04-01 20:00:00",
          "exit_ts": "2026-04-07 12:00:00",
          "entry_px": 81.1954,
          "exit_px": 78.8247,
          "pnl": -4.1417,
          "invest": 125.2149,
          "win": false,
          "pnl_pct": -3.3077,
          "exit_reason": "trail_stop",
          "entry_fng": 8,
          "exit_fng": 11,
          "bars_held": 35,
          "hours_held": 140
        },
        {
          "ticker": "DOGE-USD",
          "entry_ts": "2026-03-27 04:00:00",
          "exit_ts": "2026-04-07 20:00:00",
          "entry_px": 0.0921,
          "exit_px": 0.095,
          "pnl": 2.6455,
          "invest": 95.7616,
          "win": true,
          "pnl_pct": 2.7626,
          "exit_reason": "rsi_exit:68",
          "entry_fng": 13,
          "exit_fng": 11,
          "bars_held": 71,
          "hours_held": 284
        },
        {
          "ticker": "SOL-USD",
          "entry_ts": "2026-04-12 00:00:00",
          "exit_ts": "2026-04-13 20:00:00",
          "entry_px": 82.4783,
          "exit_px": 86.6738,
          "pnl": 4.6544,
          "invest": 99.7325,
          "win": true,
          "pnl_pct": 4.6669,
          "exit_reason": "rsi_exit:67",
          "entry_fng": 16,
          "exit_fng": 12,
          "bars_held": 12,
          "hours_held": 48
        },
        {
          "ticker": "BTC-USD",
          "entry_ts": "2026-04-12 12:00:00",
          "exit_ts": "2026-04-13 20:00:00",
          "entry_px": 70906.8203,
          "exit_px": 74532.7422,
          "pnl": 2.9959,
          "invest": 63.8288,
          "win": true,
          "pnl_pct": 4.6936,
          "exit_reason": "rsi_exit:70",
          "entry_fng": 16,
          "exit_fng": 12,
          "bars_held": 9,
          "hours_held": 36
        },
        {
          "ticker": "DOGE-USD",
          "entry_ts": "2026-04-12 00:00:00",
          "exit_ts": "2026-04-14 12:00:00",
          "entry_px": 0.0913,
          "exit_px": 0.0957,
          "pnl": 3.531,
          "invest": 79.786,
          "win": true,
          "pnl_pct": 4.4256,
          "exit_reason": "rsi_exit:67",
          "entry_fng": 16,
          "exit_fng": 21,
          "bars_held": 16,
          "hours_held": 64
        },
        {
          "ticker": "BTC-USD",
          "entry_ts": "2026-06-03 00:00:00",
          "exit_ts": "2026-06-04 04:00:00",
          "entry_px": 65748.8203,
          "exit_px": 63540.75,
          "pnl": -5.7274,
          "invest": 152.9531,
          "win": false,
          "pnl_pct": -3.7445,
          "exit_reason": "trail_stop",
          "entry_fng": 11,
          "exit_fng": 12,
          "bars_held": 8,
          "hours_held": 32
        },
        {
          "ticker": "SOL-USD",
          "entry_ts": "2026-06-03 00:00:00",
          "exit_ts": "2026-06-04 04:00:00",
          "entry_px": 72.61,
          "exit_px": 69.09,
          "pnl": -3.9183,
          "invest": 74.947,
          "win": false,
          "pnl_pct": -5.2281,
          "exit_reason": "trail_stop",
          "entry_fng": 11,
          "exit_fng": 12,
          "bars_held": 8,
          "hours_held": 32
        },
        {
          "ticker": "ETH-USD",
          "entry_ts": "2026-06-03 00:00:00",
          "exit_ts": "2026-06-04 08:00:00",
          "entry_px": 1825.3,
          "exit_px": 1749.3,
          "pnl": -4.868,
          "invest": 107.0672,
          "win": false,
          "pnl_pct": -4.5467,
          "exit_reason": "trail_stop",
          "entry_fng": 11,
          "exit_fng": 12,
          "bars_held": 9,
          "hours_held": 36
        },
        {
          "ticker": "DOGE-USD",
          "entry_ts": "2026-06-04 04:00:00",
          "exit_ts": "2026-06-05 12:00:00",
          "entry_px": 0.0887,
          "exit_px": 0.0815,
          "pnl": -9.9048,
          "invest": 117.9392,
          "win": false,
          "pnl_pct": -8.3982,
          "exit_reason": "trail_stop",
          "entry_fng": 12,
          "exit_fng": 12,
          "bars_held": 9,
          "hours_held": 36
        },
        {
          "ticker": "SOL-USD",
          "entry_ts": "2026-06-04 08:00:00",
          "exit_ts": "2026-06-06 00:00:00",
          "entry_px": 68.62,
          "exit_px": 62.81,
          "pnl": -7.0001,
          "invest": 79.2521,
          "win": false,
          "pnl_pct": -8.8327,
          "exit_reason": "trail_stop",
          "entry_fng": 12,
          "exit_fng": 12,
          "bars_held": 11,
          "hours_held": 44
        },
        {
          "ticker": "BTC-USD",
          "entry_ts": "2026-06-04 08:00:00",
          "exit_ts": "2026-06-14 20:00:00",
          "entry_px": 62472.6797,
          "exit_px": 65707.5,
          "pnl": 5.3865,
          "invest": 113.2172,
          "win": true,
          "pnl_pct": 4.7577,
          "exit_reason": "rsi_exit:68",
          "entry_fng": 12,
          "exit_fng": 18,
          "bars_held": 64,
          "hours_held": 256
        },
        {
          "ticker": "ETH-USD",
          "entry_ts": "2026-06-05 12:00:00",
          "exit_ts": "2026-06-14 20:00:00",
          "entry_px": 1582.5,
          "exit_px": 1724.73,
          "pnl": 7.5162,
          "invest": 87.8868,
          "win": true,
          "pnl_pct": 8.5522,
          "exit_reason": "rsi_exit:66",
          "entry_fng": 12,
          "exit_fng": 18,
          "bars_held": 57,
          "hours_held": 228
        },
        {
          "ticker": "DOGE-USD",
          "entry_ts": "2026-06-06 00:00:00",
          "exit_ts": "2026-06-15 12:00:00",
          "entry_px": 0.0811,
          "exit_px": 0.0906,
          "pnl": 9.3982,
          "invest": 83.1963,
          "win": true,
          "pnl_pct": 11.2964,
          "exit_reason": "rsi_exit:66",
          "entry_fng": 12,
          "exit_fng": 20,
          "bars_held": 58,
          "hours_held": 232
        }
      ]
    }
  }
}